{
  "version": "0.4.8",
  "flags": {},
  "shapes": [
    {
      "label": "T",
      "text": "",
      "points": [
        [
          58.13062973320484,
          538.004523485899
        ],
        [
          226.59910798072815,
          1138.9054123163223
        ]
      ],
      "group_id": null,
      "shape_type": "rectangle",
      "flags": {}
    }
  ],
  "imagePath": "02-08-41_002_3_scale_2.5_aug_20250806_212325.jpg",
  "imageData": null,
  "imageHeight": 1167,
  "imageWidth": 255,
  "text": ""
}