{
  "version": "0.4.8",
  "flags": {},
  "shapes": [
    {
      "label": "C",
      "text": "",
      "points": [
        [
          109.5512820512821,
          934.7820512820513
        ],
        [
          217.24358974358972,
          1157.8589743589744
        ]
      ],
      "group_id": null,
      "shape_type": "rectangle",
      "flags": {}
    },
    {
      "label": "T",
      "text": "",
      "points": [
        [
          62.11538461538464,
          265.55128205128204
        ],
        [
          190.32051282051282,
          560.4230769230769
        ]
      ],
      "group_id": null,
      "shape_type": "rectangle",
      "flags": {}
    },
    {
      "label": "T",
      "text": "",
      "points": [
        [
          190.32051282051282,
          1.4487179487179427
        ],
        [
          254.0,
          204.0
        ]
      ],
      "group_id": null,
      "shape_type": "rectangle",
      "flags": {}
    },
    {
      "label": "C",
      "text": "",
      "points": [
        [
          73.65384615384619,
          123.24358974358972
        ],
        [
          176.21794871794884,
          228.37179487179486
        ]
      ],
      "group_id": null,
      "shape_type": "rectangle",
      "flags": {}
    }
  ],
  "imagePath": "03-08-30_002_1_scale_2.5.jpg",
  "imageData": null,
  "imageHeight": 1167,
  "imageWidth": 255,
  "text": ""
}